ytsr/__init__.py
ytsr-2.0.0.dist-info/METADATA
ytsr-2.0.0.dist-info/RECORD
ytsr-2.0.0.dist-info/WHEEL
ytsr-2.0.0.dist-info/top_level.txt
