Metadata-Version: 2.1
Name: ytsr
Version: 2.0.0
Summary: Youtube Search
Home-page: https://github.com/pypa/sampleproject
Author: Bandi B
Author-email: laandro3@gmail.com
License: UNKNOWN
Platform: UNKNOWN
Classifier: Programming Language :: Python :: 3
Classifier: License :: OSI Approved :: MIT License
Classifier: Operating System :: OS Independent
